{
  "generated": "2026-07-20T06:34:18.683953",
  "analysis": {
    "market_pulse": {
      "top_3_trending_topics": [
        "Mind-Blowing Facts",
        "Space and Astronomy",
        "Science Experiments"
      ],
      "top_3_trending_hook_styles": [
        "Using emojis to create curiosity \ud83e\udd2f",
        "Asking questions to encourage engagement \ud83e\udd14",
        "Making bold statements to create surprise \ud83d\ude31"
      ],
      "avg_engagement_rate": "2.13%",
      "best_performing_content_type": "Short, visually engaging videos with a mix of experiments and interesting facts",
      "viral_trigger": "Using attention-grabbing titles and thumbnails that create curiosity and surprise"
    },
    "competitor_intelligence": {
      "winning_channels": [
        "Kurzgesagt \u2013 In a Nutshell",
        "The Slow Mo Guys"
      ],
      "their_secret": "Creating high-quality, engaging content that is both informative and entertaining",
      "title_patterns": [
        "Using questions in titles",
        "Creating curiosity with titles",
        "Using emojis in titles"
      ],
      "hook_patterns": [
        "Starting with a surprising fact",
        "Asking a question to encourage engagement",
        "Using a personal story to connect with viewers"
      ],
      "topics_they_avoid": [
        "Sensitive or controversial topics",
        "Overly complex or technical topics"
      ]
    },
    "my_channel_diagnosis": {
      "best_performing_video": "\ud83c\udf0c Poisonous Skies Revealed",
      "worst_performing_video": "\ud83d\udd0d The Hidden Truth About Reality",
      "my_strengths": [
        "Creating engaging titles and thumbnails",
        "Covering a wide range of interesting topics"
      ],
      "my_gaps": [
        "Lack of consistency in content quality",
        "Not utilizing hashtags and tags effectively"
      ],
      "retention_problem": "Viewers are dropping off due to lack of engagement and inconsistent content quality"
    },
    "content_opportunities": [
      {
        "rank": 1,
        "topic": "The Science of Black Holes",
        "why": "High engagement rate on similar topics and a lack of content on this specific topic",
        "hook": "What if I told you that black holes are not just vacuum cleaners in space?",
        "title": "\ud83d\udd2e The Mind-Blowing Truth About Black Holes",
        "estimated_performance": "high",
        "urgency": "The topic of black holes is currently trending and has a high engagement rate"
      },
      {
        "rank": 2,
        "topic": "The Mystery of Fast Radio Bursts",
        "why": "High engagement rate on similar topics and a lack of content on this specific topic",
        "hook": "Imagine a burst of energy so powerful that it can be seen from millions of light-years away",
        "title": "\ud83c\udf1f The Cosmic Enigma of Fast Radio Bursts",
        "estimated_performance": "medium",
        "urgency": "The topic of fast radio bursts is currently trending and has a high engagement rate"
      },
      {
        "rank": 3,
        "topic": "The Science of Dreams",
        "why": "High engagement rate on similar topics and a lack of content on this specific topic",
        "hook": "What if I told you that your dreams are not just random thoughts, but a window into your subconscious mind?",
        "title": "\ud83e\udde0 The Fascinating Science of Dreams",
        "estimated_performance": "medium",
        "urgency": "The topic of dreams is currently trending and has a high engagement rate"
      }
    ],
    "next_video_brief": {
      "topic": "The Science of Black Holes",
      "hook": "What if I told you that black holes are not just vacuum cleaners in space?",
      "script_direction": "Create a visually engaging video that explains the science behind black holes, including their formation, characteristics, and effects on the surrounding space",
      "title": "\ud83d\udd2e The Mind-Blowing Truth About Black Holes",
      "tags": [
        "black holes",
        "space",
        "astronomy",
        "science",
        "cosmos"
      ],
      "hashtags": [
        "#blackholes",
        "#space",
        "#astronomy",
        "#science"
      ],
      "thumbnail_concept": "A visually striking image of a black hole, with a bold and eye-catching title",
      "confidence_score": 85
    },
    "strategic_recommendations": [
      "Create a content calendar to ensure consistency and organization",
      "Utilize hashtags and tags more effectively to increase discoverability",
      "Collaborate with other creators or experts in the field to create high-quality and engaging content"
    ]
  }
}