{
  "generated": "2026-06-15T09:45:23.893985",
  "analysis": {
    "market_pulse": {
      "top_3_trending_topics": [
        "space and physics",
        "mind-blowing science facts",
        "kitchen hacks and secrets"
      ],
      "top_3_trending_hook_styles": [
        "using emojis to create curiosity",
        "asking a thought-provoking question",
        "making a bold statement"
      ],
      "avg_engagement_rate": "1.53%",
      "best_performing_content_type": "short, informative videos with a mix of visuals and text overlays",
      "viral_trigger": "using a combination of surprising facts and eye-catching thumbnails"
    },
    "competitor_intelligence": {
      "winning_channels": [
        "Kurzgesagt \u2013 In a Nutshell",
        "The Slow Mo Guys"
      ],
      "their_secret": "creating high-quality, engaging content that is both informative and entertaining",
      "title_patterns": [
        "using action words like 'reveals' and 'exposed'",
        "including relevant keywords like 'space' and 'science'",
        "asking questions that pique the viewer's curiosity"
      ],
      "hook_patterns": [
        "starting with a surprising fact or statistic",
        "using humor or irony to grab the viewer's attention",
        "creating a sense of mystery or intrigue"
      ],
      "topics_they_avoid": [
        "overly complex or technical topics",
        "topics that are too similar to their previous content"
      ]
    },
    "my_channel_diagnosis": {
      "best_performing_video": "\ud83d\ude80 Black Holes: Gravity's Kill Switch",
      "worst_performing_video": "\ud83d\ude80 Bullet Orbit: Mars Gunfire Secret",
      "my_strengths": [
        "creating engaging thumbnails",
        "using relevant keywords in titles and tags"
      ],
      "my_gaps": [
        "lack of consistency in content style and quality",
        "not utilizing hooks and patterns effectively"
      ],
      "retention_problem": "viewers are dropping off due to lack of engagement and inconsistent content quality"
    },
    "content_opportunities": [
      {
        "rank": 1,
        "topic": "the physics of black holes",
        "why": "high engagement rate and views on similar topics",
        "hook": "What if I told you that black holes are not just vacuum cleaners in space?",
        "title": "The Mind-Blowing Physics of Black Holes",
        "estimated_performance": "high",
        "urgency": "the topic is currently trending and has a high engagement rate"
      },
      {
        "rank": 2,
        "topic": "kitchen hacks and secrets",
        "why": "high views and engagement rate on similar topics",
        "hook": "You won't believe the secret ingredient that will change your cooking forever",
        "title": "The Dark Science of Kitchen Hacks",
        "estimated_performance": "medium",
        "urgency": "the topic is currently popular and has a high engagement rate"
      },
      {
        "rank": 3,
        "topic": "space and astronomy",
        "why": "high engagement rate and views on similar topics",
        "hook": "What if I told you that there is a planet that is completely covered in worms?",
        "title": "The Weird and Wonderful World of Space",
        "estimated_performance": "medium",
        "urgency": "the topic is currently trending and has a high engagement rate"
      }
    ],
    "next_video_brief": {
      "topic": "the physics of black holes",
      "hook": "What if I told you that black holes are not just vacuum cleaners in space?",
      "script_direction": "Create a engaging and informative video that explores the physics of black holes, including their formation, behavior, and effects on the surrounding space. Use a mix of visuals and text overlays to keep the viewer engaged.",
      "title": "The Mind-Blowing Physics of Black Holes",
      "tags": [
        "black holes",
        "physics",
        "space",
        "astronomy",
        "science"
      ],
      "hashtags": [
        "#shorts",
        "#blackholes",
        "#space"
      ],
      "thumbnail_concept": "a visually striking image of a black hole, with a bold and eye-catching title overlay",
      "confidence_score": 85
    },
    "strategic_recommendations": [
      "Create a consistent content style and quality to improve viewer engagement and retention",
      "Utilize hooks and patterns effectively to grab the viewer's attention and keep them engaged",
      "Focus on creating high-quality, engaging content that is both informative and entertaining"
    ]
  }
}